LICENSE.md
gns3inspector/main.py
gns3inspector-1.0.2.dist-info/entry_points.txt
gns3inspector-1.0.2.dist-info/LICENSE.md
gns3inspector-1.0.2.dist-info/WHEEL
gns3inspector-1.0.2.dist-info/METADATA
gns3inspector-1.0.2.dist-info/RECORD
