Metadata-Version: 2.1
Name: gns3inspector
Version: 1.0.2
Summary: Tool to easier view and edit the router's configuration files in GNS3
Home-page: https://github.com/fjellvannet/GNS3Inspector.git
License: ISC
Author: Lukas Neuenschwander
Author-email: fjellvannet@gmail.com
Requires-Python: >=3.8,<4.0
Classifier: License :: OSI Approved
Classifier: Programming Language :: Python :: 3
Classifier: Programming Language :: Python :: 3.8
Classifier: Programming Language :: Python :: 3.9
Classifier: Programming Language :: Python :: 3.10
Requires-Dist: PyYAML (>=6.0,<7.0)
Requires-Dist: black (>=22.10.0,<23.0.0)
Requires-Dist: click (>=8.1.3,<9.0.0)
Requires-Dist: fagus (>=1.0.1,<2.0.0)
Requires-Dist: readline (>=6.2.4.1,<7.0.0.0)
Requires-Dist: rich (>=12.6.0,<13.0.0)
Project-URL: Repository, https://github.com/fjellvannet/GNS3Inspector.git
